sbretrieval/__init__.py
sbretrieval/ai_models/__init__.py
sbretrieval/ai_models/gemini.py
sbretrieval/ai_models/openai.py
sbretrieval/database.py
sbretrieval/exceptions.py
sbretrieval/public.py
sbretrieval-0.5.0.dist-info/METADATA
sbretrieval-0.5.0.dist-info/WHEEL
sbretrieval-0.5.0.dist-info/RECORD
