Metadata-Version: 2.1
Name: sbretrieval
Version: 0.5.0
Summary: Document search and indexing based on summaries and embeddings, using pgvector
Author: talles-frwk
Author-email: talleslasmar@frwk.com.br
Requires-Python: >=3.12,<4.0
Classifier: Programming Language :: Python :: 3
Classifier: Programming Language :: Python :: 3.12
Classifier: Programming Language :: Python :: 3.13
Requires-Dist: asyncpg (>=0.30.0,<0.31.0)
Requires-Dist: google-generativeai (>=0.8.3,<0.9.0)
Requires-Dist: openai (>=1.57.2,<2.0.0)
Requires-Dist: tiktoken (>=0.8.0,<0.9.0)
